virtuallinks/__init__.py
virtuallinks/virtuallinks.py
virtuallinks-0.0.1.dist-info/DESCRIPTION.rst
virtuallinks-0.0.1.dist-info/METADATA
virtuallinks-0.0.1.dist-info/RECORD
virtuallinks-0.0.1.dist-info/WHEEL
virtuallinks-0.0.1.dist-info/metadata.json
virtuallinks-0.0.1.dist-info/pbr.json
virtuallinks-0.0.1.dist-info/top_level.txt
