Metadata-Version: 2.0
Name: virtuallinks
Version: 0.0.1
Summary: A simulator of file system links.
Home-page: https://github.com/ffunenga/virtuallinks
Author: Filipe Funenga
Author-email: fmafunenga@gmail.com
License: MIT
Platform: UNKNOWN
